wiki_dump_extractor/__init__.py
wiki_dump_extractor/date_utils.py
wiki_dump_extractor/download_utils.py
wiki_dump_extractor/llm_utils.py
wiki_dump_extractor/page_utils.py
wiki_dump_extractor/wiki_dump_extractor.py
wiki_dump_extractor/wiki_sql_extractor.py
wiki_dump_extractor-0.1.0.dist-info/licenses/LICENSE
wiki_dump_extractor-0.1.0.dist-info/METADATA
wiki_dump_extractor-0.1.0.dist-info/WHEEL
wiki_dump_extractor-0.1.0.dist-info/top_level.txt
wiki_dump_extractor-0.1.0.dist-info/RECORD
