Metadata-Version: 2.4
Name: wiki_dump_extractor
Version: 0.1.0
Summary: A Python package for extracting and processing Wikipedia data
Author: Zulko
License: MIT
Project-URL: Homepage, https://github.com/zulko/wiki_extractor
Classifier: Programming Language :: Python :: 3
Classifier: License :: OSI Approved :: MIT License
Classifier: Operating System :: OS Independent
Classifier: Topic :: Text Processing :: Markup
Classifier: Topic :: Scientific/Engineering :: GIS
Requires-Python: >=3.8
License-File: LICENSE
Requires-Dist: lxml>=4.9.0
Requires-Dist: fastavro>=1.0.0
Requires-Dist: zstandard>=0.23
Requires-Dist: pandas>=2.0.0
Requires-Dist: tqdm>=4.65.0
Requires-Dist: lmdb>=1.4.1
Requires-Dist: aiostream>=0.5.0
Requires-Dist: regex>=2023.12.0
Provides-Extra: llm
Requires-Dist: google-cloud-aiplatform; extra == "llm"
Requires-Dist: google-cloud-storage; extra == "llm"
Requires-Dist: google-genai; extra == "llm"
Requires-Dist: pydantic; extra == "llm"
Requires-Dist: pydantic-ai; extra == "llm"
Requires-Dist: mwparserfromhell; extra == "llm"
Provides-Extra: test
Requires-Dist: pytest>=7.0.0; extra == "test"
Requires-Dist: pytest-cov>=4.0.0; extra == "test"
Provides-Extra: docs
Requires-Dist: sphinx>=7.0.0; extra == "docs"
Requires-Dist: myst-parser>=2.0.0; extra == "docs"
Requires-Dist: shibuya==2024.10.15; extra == "docs"
Dynamic: license-file
